streambook/__init__.py
streambook/__main__.py
streambook/cli.py
streambook/gen.py
streambook/lib.py
streambook/version.py
streambook-0.3.dist-info/LICENSE
streambook-0.3.dist-info/METADATA
streambook-0.3.dist-info/WHEEL
streambook-0.3.dist-info/entry_points.txt
streambook-0.3.dist-info/top_level.txt
streambook-0.3.dist-info/RECORD
