Metadata-Version: 2.1
Name: streambook
Version: 0.3
Summary: UNKNOWN
Author: Alexander Rush
Author-email: arush@cornell.edu
License: UNKNOWN
Platform: UNKNOWN
Requires-Python: >=3.6
License-File: LICENSE
Requires-Dist: streamlit
Requires-Dist: jupytext
Requires-Dist: watchdog
Requires-Dist: in-place
Requires-Dist: mistune
Requires-Dist: typer
